directory_forms_api_client/__init__.py
directory_forms_api_client/actions.py
directory_forms_api_client/client.py
directory_forms_api_client/forms.py
directory_forms_api_client/helpers.py
directory_forms_api_client-7.5.4.dist-info/licenses/LICENSE
directory_forms_api_client-7.5.4.dist-info/METADATA
directory_forms_api_client-7.5.4.dist-info/WHEEL
directory_forms_api_client-7.5.4.dist-info/top_level.txt
directory_forms_api_client-7.5.4.dist-info/RECORD
