Metadata-Version: 2.4
Name: directory_forms_api_client
Version: 7.5.4
Summary: Python API client for Directory forms .
Home-page: https://github.com/uktrade/directory-forms-api-client
Author: Department for International Trade
License: MIT
Classifier: Development Status :: 5 - Production/Stable
Classifier: Environment :: Web Environment
Classifier: Framework :: Django
Classifier: Framework :: Django :: 1.11
Classifier: Framework :: Django :: 2.0
Classifier: Framework :: Django :: 2.1
Classifier: Framework :: Django :: 2.2
Classifier: Framework :: Django :: 3.1
Classifier: Framework :: Django :: 3.2
Classifier: Framework :: Django :: 4.2
Classifier: Intended Audience :: Developers
Classifier: License :: OSI Approved :: MIT License
Classifier: Natural Language :: English
Classifier: Operating System :: OS Independent
Classifier: Programming Language :: Python :: 3.9
Classifier: Programming Language :: Python :: 3.13
Classifier: Topic :: Software Development :: Libraries :: Python Modules
License-File: LICENSE
Requires-Dist: directory_client_core<8.0.0,>=7.2.12
Provides-Extra: test
Requires-Dist: django<5.0,>=4.2.10; extra == "test"
Requires-Dist: flake8; extra == "test"
Requires-Dist: pytest-codecov; extra == "test"
Requires-Dist: pytest-cov; extra == "test"
Requires-Dist: GitPython; extra == "test"
Requires-Dist: pytest-django==3.10.0; extra == "test"
Requires-Dist: pytest; extra == "test"
Requires-Dist: requests<3.0.0,>=2.22.0; extra == "test"
Requires-Dist: requests_mock==1.8.0; extra == "test"
Requires-Dist: setuptools; extra == "test"
Requires-Dist: twine; extra == "test"
Requires-Dist: wheel<1.0.0,>=0.34.2; extra == "test"
Requires-Dist: psycopg2; extra == "test"
Dynamic: author
Dynamic: classifier
Dynamic: description
Dynamic: description-content-type
Dynamic: home-page
Dynamic: license
Dynamic: license-file
Dynamic: provides-extra
Dynamic: requires-dist
Dynamic: summary
